scratch_getdata/__init__.py
scratch_getdata/api_client.py
scratch_getdata-1.0.8.dist-info/METADATA
scratch_getdata-1.0.8.dist-info/WHEEL
scratch_getdata-1.0.8.dist-info/top_level.txt
scratch_getdata-1.0.8.dist-info/RECORD
