Metadata-Version: 2.1
Name: scratch-getdata
Version: 1.0.8
Summary: A Module to fetch scratch things from ScratchGetData
Author: kokofixcomputers
Author-email: kokofixcomputers <kokocanfixit@kokofixcomputers.serv00.net>
Project-URL: Github, https://github.com/scratch-getdata/scratch-getdata-python
Project-URL: Bug Tracker, https://github.com/scratch-getdata/scratch-getdata-python/issues
Classifier: Programming Language :: Python :: 3
Classifier: License :: OSI Approved :: MIT License
Classifier: Operating System :: OS Independent
Requires-Python: >=3.7
Requires-Dist: requests
